Metadata-Version: 1.0
Name: morsetor
Version: 0.0.1
Summary: Morse : https://github.com/imvickykumar999/git-bash/tree/master
Home-page: https://vixportfoliowithflask.herokuapp.com/skills
Author: Vicky Kumar
Author-email: UNKNOWN
License: MIT
Keywords: GitHub Uploader,Morse,custom,python package,function and class,3D line,3D plane,angle bw planes or line,distance bw point and plane
Platform: UNKNOWN
